deaduction/__init__.py
deaduction/version.py
deaduction/dui/__init__.py
deaduction/dui/__main__.py
deaduction/dui/elements/__init__.py
deaduction/dui/elements/actions_widgets_classes.py
deaduction/dui/elements/config_window.py
deaduction/dui/elements/config_window_text.py
deaduction/dui/elements/context_widgets_classes.py
deaduction/dui/elements/goal_widgets.py
deaduction/dui/elements/help.py
deaduction/dui/elements/html_list_view.py
deaduction/dui/elements/lean_editor.py
deaduction/dui/elements/menubar.py
deaduction/dui/elements/proof_outline_widget.py
deaduction/dui/elements/recent_courses_widgets.py
deaduction/dui/elements/start_coex_widget_classes.py
deaduction/dui/elements/statusbar.py
deaduction/dui/elements/proof_tree/__init__.py
deaduction/dui/elements/proof_tree/proof_tree_controller.py
deaduction/dui/elements/proof_tree/proof_tree_primitives.py
deaduction/dui/elements/proof_tree/proof_tree_widget.py
deaduction/dui/primitives/__init__.py
deaduction/dui/primitives/base_math_widgets_styling.py
deaduction/dui/primitives/buttons_dialog.py
deaduction/dui/primitives/disclosure_dict.py
deaduction/dui/primitives/disclosure_triangle.py
deaduction/dui/primitives/font_config.py
deaduction/dui/primitives/radio_tool_button.py
deaduction/dui/primitives/rich_tool_button.py
deaduction/dui/primitives/text_edit_logger.py
deaduction/dui/primitives/yes_no_dialog.py
deaduction/dui/stages/__init__.py
deaduction/dui/stages/calculator/__init__.py
deaduction/dui/stages/calculator/calculator.py
deaduction/dui/stages/calculator/calculator_button.py
deaduction/dui/stages/calculator/calculator_targets.py
deaduction/dui/stages/exercise/Coordinator.py
deaduction/dui/stages/exercise/__init__.py
deaduction/dui/stages/exercise/_exercise_main_window_widgets.py
deaduction/dui/stages/exercise/coordinator_mode.py
deaduction/dui/stages/exercise/exercise_main_window.py
deaduction/dui/stages/missing_dependencies/__init__.py
deaduction-0.3.99985.dist-info/METADATA
deaduction-0.3.99985.dist-info/WHEEL
deaduction-0.3.99985.dist-info/entry_points.txt
deaduction-0.3.99985.dist-info/licenses/LICENSE.md
deaduction-0.3.99985.dist-info/RECORD
