Metadata-Version: 2.4
Name: deaduction
Version: 0.3.99985
Summary: Graphical proof assistant for learning proofs
Project-URL: Homepage, https://github.com/dEAduction/dEAduction
Project-URL: Documentation, https://github.com/dEAduction/dEAduction/wiki
Project-URL: Repository, https://github.com/dEAduction/dEAduction
Project-URL: Issues, https://github.com/dEAduction/dEAduction/issues
Author-email: Marguerite Bin <bin.marguerite@gmail.com>, Florian Dupeyron <florian.dupeyron@mugcat.fr>, Frédéric Le Roux <frederic.le-roux@imj-prg.fr>, Antoine Leudière <hg4fpchw@anonaddy.me>
Maintainer-email: Frédéric Le Roux <frederic.le-roux@imj-prg.fr>
License:                     GNU GENERAL PUBLIC LICENSE
License-File: LICENSE.md
Keywords: logic,mathematics,proofs
Classifier: License :: OSI Approved :: GNU General Public License v3 or later (GPLv3+)
Classifier: Operating System :: OS Independent
Classifier: Programming Language :: Python :: 3
Requires-Python: >=3.7
Requires-Dist: dictdiffer>=0.8.1
Requires-Dist: diff-match-patch>=20200713
Requires-Dist: parsimonious>=0.8.1
Requires-Dist: pickle5>=0.0.11; python_version < '3.8'
Requires-Dist: pyside2>=5.13.2
Requires-Dist: pytest>=5.4.3
Requires-Dist: qtrio>=0.5.1
Requires-Dist: requests>=2.24.0
Requires-Dist: toml>=0.10.1
Requires-Dist: tomli-w
Requires-Dist: trio>=0.16.0
